{"airship":{"bgm":{"name":"Ship3","pan":0,"pitch":100,"volume":90},"characterIndex":3,"characterName":"Vehicle","startMapId":0,"startX":0,"startY":0},"armorTypes":["","#{termwords.generalarmor}","#{termwords.clotharmor}","#{termwords.lightarmor}","#{termwords.heavyarmor}","#{termwords.smallshield}","#{termwords.largeshield}","#{termwords.head}","#{termwords.accessory}"],"attackMotions":[{"type":0,"weaponImageId":0},{"type":1,"weaponImageId":1},{"type":1,"weaponImageId":2},{"type":1,"weaponImageId":3},{"type":1,"weaponImageId":4},{"type":1,"weaponImageId":5},{"type":1,"weaponImageId":6},{"type":2,"weaponImageId":7},{"type":2,"weaponImageId":8},{"type":2,"weaponImageId":9},{"type":0,"weaponImageId":10},{"type":0,"weaponImageId":11},{"type":0,"weaponImageId":12},{"type":1,"weaponImageId":29},{"type":2,"weaponImageId":23}],"battleBgm":{"name":"Wingless_Battle-forHonor_loop","pan":0,"pitch":100,"volume":90},"battleback1Name":"Grassland","battleback2Name":"Grassland","battlerHue":0,"battlerName":"","boat":{"bgm":{"name":"Ship1","pan":0,"pitch":100,"volume":90},"characterIndex":0,"characterName":"Vehicle","startMapId":0,"startX":0,"startY":0},"currencyUnit":"#{termwords.gold}","defeatMe":{"name":"Defeat1","pan":0,"pitch":100,"volume":90},"editMapId":3,"elements":["","#{termwords.physical}","\\i[64]\\c[18]#{termwords.fire}","\\i[65]\\c[23]#{termwords.ice}","\\i[66]\\c[17]#{termwords.thunder}","\\i[67]\\c[9]#{termwords.water}","\\i[68]\\c[20]#{termwords.earth}","\\i[69]\\c[3]#{termwords.wind}","\\i[70]\\c[6]#{termwords.holy}","\\i[71]\\c[30]#{termwords.darkness}","\\i[2021]\\c[11]#{termwords.plant}","\\i[10]\\c[7]#{termwords.undead}","\\i[2026]\\c[27]#{termwords.puremagic}","\\i[3754]\\c[8]#{termwords.blackmagic}","\\i[97]#{termwords.slash}","\\i[107]#{termwords.pierce}","\\i[98]#{termwords.blunt}","","","",""],"equipTypes":["","#{termwords.weapon}","#{termwords.shield}","#{termwords.head}","#{termwords.body}","#{termwords.accessory}"],"gameTitle":"Yggdrasil Chronicles: A Record of Valkadia","gameoverMe":{"name":"Gameover1","pan":0,"pitch":100,"volume":90},"locale":"en_US","magicSkills":[],"menuCommands":[true,true,true,true,true,true],"optDisplayTp":true,"optDrawTitle":false,"optExtraExp":true,"optFloorDeath":false,"optFollowers":true,"optSideView":true,"optSlipDeath":true,"optTransparent":false,"partyMembers":[1],"ship":{"bgm":{"name":"21 Advancing sea","pan":0,"pitch":100,"volume":90},"characterIndex":1,"characterName":"Vehicle","startMapId":27,"startX":8,"startY":7},"skillTypes":["","#{termwords.magic}","#{termwords.ability}","#{termwords.aid}","#{termwords.passive}","#{termwords.ultimate}","Stats Investment","","","",""],"sounds":[{"name":"Cursor2","pan":0,"pitch":100,"volume":90},{"name":"Decision1","pan":0,"pitch":100,"volume":90},{"name":"Cancel2","pan":0,"pitch":100,"volume":90},{"name":"Buzzer1","pan":0,"pitch":100,"volume":90},{"name":"Equip1","pan":0,"pitch":100,"volume":90},{"name":"Save","pan":0,"pitch":100,"volume":90},{"name":"Load","pan":0,"pitch":100,"volume":90},{"name":"Battle4","pan":0,"pitch":100,"volume":90},{"name":"Run","pan":0,"pitch":100,"volume":90},{"name":"Attack3","pan":0,"pitch":100,"volume":90},{"name":"Damage4","pan":0,"pitch":100,"volume":90},{"name":"Collapse1","pan":0,"pitch":100,"volume":90},{"name":"Collapse2","pan":0,"pitch":100,"volume":90},{"name":"Collapse3","pan":0,"pitch":100,"volume":90},{"name":"Damage5","pan":0,"pitch":100,"volume":90},{"name":"Collapse4","pan":0,"pitch":100,"volume":90},{"name":"Recovery","pan":0,"pitch":100,"volume":90},{"name":"Miss","pan":0,"pitch":100,"volume":90},{"name":"Evasion1","pan":0,"pitch":100,"volume":90},{"name":"Evasion2","pan":0,"pitch":100,"volume":90},{"name":"Reflection","pan":0,"pitch":100,"volume":90},{"name":"Shop1","pan":0,"pitch":100,"volume":90},{"name":"Item3","pan":0,"pitch":100,"volume":90},{"name":"Item3","pan":0,"pitch":100,"volume":90}],"startMapId":3,"startX":4,"startY":7,"switches":["","Game Start","Two Guards Down","Break Prison","Guards Appear","Guards Down","Talk About Contract","Next Day in Morrigan House","Find Lilith","Get out of house","Check Shops","Go To Magic Shop","Enter Sunlight River","Explore Moonlight Cave","Take Pouch","Get out of Moonlight Cave","Show Files","Remove Lydia","Enter Religia","First Time To Religia","To The Tavern","Show Beers","Break Table","Out of tavern","To Big Joe Mansion","Check Culverts","Approach Blanc","Blanc Joins","Give Meal","Approach Plati","Out of Mansion","Start Timer","Prepare Meal","Blanc Rest","Talk To Harley 2","Back To House","To Lost Forest","First Time To Seagull","Go to 2F Anti Servant","Back To Haravi","First Time To Haravi","Talk To Father Albert","Move Shelf","Took Crystal","To Coal Mine","Explore Coal Mine","Take Pickaxe","Activate Detection","Sinister Wraith Killed","Open Chest","Back To Summerbreeze","Dynamites Exploded","To Sanguine Ocean","First Time Sail","Locate Ships","Found Ships","Spyglass","Done SpyGlass","Onward to Rescue Cargo","Storm Activate","Delete Ships","Pirate Death","Back To HQ from Ocean","Explore Whirlwind","Found Relic","Engage Wolf","Break Relic","Relic Appears","Relic Ready","Relic Destroyed","Portal Appears","Portal Disappears","Back To Seagull From Island","Back To HQ","To Sandstorm Oasis","Activate Teleport & Craft Gem","Money Appears","Bandits Died","Takes Money Back","To Merinberg","First Time To Merinberg","First Time To Merin inn","Blanc Wake Up","Enter City Hall","Inside City Hall","Bring Contract to Vincent","Special Force Down","Take Contract Back","Speak With Helena","Onto Merin Peak","Approach Kyungri","Clear Creeps","Into The Tomb","Wall Cracked","Gate Opens","Azure Sphere Taken","Firebird Ritual","Firebird Portal","Open Chest Deep ocean","Firebird Dies","Take Feather","Guards Leave","Talk To Crawforde","Enter Rest Room","Out of City Hall","Amelia Attacks Merinberg","Remove Guards","Take Chaos Shard","Back To City Hall","To WhiteHaven","Door Exposed","Stone Disappears","Gate Opened","Bridge Appeared","Torch 1","Torch 2","Torch 3","Torch 4","Portal Opens","Enter Blanc House","Scout Whitehaven","Aiko Lucas Join","Abort Lucas Battle","Violent Dust Chest","Summerbreeze Town Attacked","Find Morrigan","Ryan Left","Inside Verdurous","Leave Verdurous","Onto Luvinia","Lilith Darkness Power","End Battle With Subject M","Take Light","Voiceless Lightrays Off","Entered Abbey","Sister Cristiona Back","Find Zephaniah Office","Talk To Zephaniah","Go To Spirit Well","Back To Haravi","Defeated Shadow Fiend","Destiny Bond Activate","Enter Morrigan House Again","Morrigan Awake","Night Rest","Next Day","Done Letter","Activate SF","Report Back To Father","Father Leave","Head To Valenka","Write Letter","Prevent From Valenka","To Chaotic Swamp","Bandits Out","Bandits Died","Showing Merchant Card","Into The Inn","Guests Leave","To Valenka Cathedral","Into Valenka Royal Palace","First Time To Royal Done","Check on Einhart","Gather at office","Summerbreeze Wasted Back","To the Labyrinth","Approach Shard of Tranquil","Teamates Appear","Black Knight Dead","Shard out","Einhard Appears In","Members Disappear","To Valenka Shop","To Item Shop","Kyungri Appears","Receive Rood","Gather Withered Bone","Look For Kyungri","Look For Kyungri 2","Look For Kyungri 3","Kyungri In Valenka Outpost","Bring Hammer To Han","Start Forging Cube","Meet King Cedric Wisebrook","Finish Talk With King","Get The Purging Cube","Deliver Cube to Einhart","Enter Amelia's Room","Remove Kyungri","Activate Amelia Tool","Activate Crystals","Activate Portal","Enter The Void","Amelia Chest","Einhart Focus","Subject A Appears","After Subject A Battle","Necklace Dropped","Subject A Hit","Amelia Left","Pickup Necklace","Take Plati to Einhart","Talk To Receptionists For Plati","To Seishin Wood","Enter Shiroyuki Town","First Time In Shiroyuki","Disable Magic Shop Tut","Look For Plati In Shiroyuki","Have A Word with Ryland","Take Plati Back To Valenka","Enter Blistering Flame Temple","Lucas Throw","Blistering Temple Collapsed","Return To Valenka To See Einhart","Check on Plati","Go To Valenka Alchemist","Return To Shiroyuki","Ryland leaves","Go to Kaoru's House","Enter Kaoru's lab","Dig Grave","Back To Valenka To Meet Einhart","Plati Appears","Back To Voiceless Jungle","A & M Leave","Subject M Battle Ends","Lydia Last Moment","Shard Appears","Meet Einhart at Tower","To Shiroyuki Dock","To Azure Sea","Bridge Appears","Random Elf Appears","Bridge Puzzle","Activate Circle Ack","First Time In Serenus","Enter Balthazar Academy","Professor Balthazar Appears","Go To Balthazar Office","Doctor Niveus Appears","To Niveus Lab","","","","","","","","","","","","","","","","","","","","","","","","","","","","","","","","","","","","","","","","","","","","","","","","","","","","","","","","","","","","","","","","","","","","","","","","","","","","","","","","","","","","","","","","","","","","","","","","","","","","","","","","","","","","","","","","","","","","","","","","","","","","","","","","","","","","","","","","","","","","","","","","","","","","","","","","","","","","","","","","","","","","","","","","","","","","","","","","","","","","","","","","","","","","","","","","","","","","","","","","","","","","","","","","","","","","","","","","","","","","","","","","","","","","","","","","","","","","","","","","","","","","","","","","","","","","","","","","","","","","","","","","","","","","","","","","","","","","","","","","","","","","","","","","","","","","","","","","","","","","","","","","","","","","","","","","","","","","","","","","","","","","","","","","","","","","","","","","","","","","","","","","","","","","","","","","","","","","","","","","","","","","","","","","","","","","","","","","","","","","","","","","","","","","","","","","","","","","","","","","","","","","","","","","","","","","","","","","","","","","","","","","","","","","","","","","","","","","","","","","","","","","","","","","","","","","","","","","","","","","","","","","","","","","","","","","","","","","","","","","","","","","","","","","","","","","","","","","","","","","","","","","","","","","","","","","","","","","","","","","","","","","","","","","","","","","","","","","","","","","","","","","","","","","","","","","","","","","","","","","","","","","","","","","","","","","","","","","","","","","","","","","","","","","","","","","","","","","","","","","","","","","","","","","","","","","","","","","","","","","","","","","","","","","","","","","","","","","","","","","","","","","","","","","","","","","","","","","","","","","","","","","","","","","","","","","","","","","","","","","","","","","","","","","","","","","","","","","","","","","","","","","","","","","","","","","","","","","","","","","","","","","","","","","","","","","","","","","","","","","","","","","","","","","","","","","","","","","","","","","Debug Unlock Potential Skills","Dawn = 3am – 5am","Sunrise = 6am – 8am","Day = 9am – 14pm","Sunset = 15pm – 17pm","Dusk = 18pm – 20pm","Night = 21pm – 2am","Day Shift = 9am – 18pm","Night Shift = 21pm – 6am","Monday","Tuesday","Wednesday","Thursday","Friday","Saturday","Sunday","January","February","March","April","May","June","July","August","September","October","November","December","Spring","Summer","Autumn","Winter","--------Lighting--------","Turn On Light","Disable Ambient Light","Turn On Window Yellow Light","Turn On Window Orange Light","Turn On Window White Light","Disable Teleport System","Turn On Oil Lamp","Turn On Light Rays","Morrigan Potential","Lilith Potential","Blanc Potential","Leo Potential","Aiko Potential","Lucas Potential","Battle Tutorial Switch Attack","Battle Tutorial Switch Aid","Battle Tutorial Switch Skill","Battle Tutorial Switch Guard","Battle Tut Check","Battle Tutorial Switch Item","Battle Tutorial Switch Ultimate","Battle Tutorial Switch Victory","Ship Dock Shiroyuki","Ship Dock Seagull","Ship Dock Serene","","","","","","","","","","","","","","","","","","","","","","","","","","","","","","","","","","","","","","","","","","","","[Tele] Summerbreeze","[Tele] Religia","[Tele] Seagull","[Tele] Haravi","[Tele] Merinberg","[Tele] Whitehaven","Disable Boat In Valenka","[Tele] Luvinia","[Tele] Valenka","[Tele] Shiroyuki","[Tele] Serenus","","","","","","","","","","","","","","","","","","","","","","","","","","","","","","","","","","","","","","","","","","","","","","","","","","","","","","","","","","","","","","","","","","","","","","","","","","","","","","","","","","","","","","","","","","","","","","","","","","","","","","","","","","","","","","","","","","","","","","","","","","","","","","","","","","","","","","","","","","","","","","","","","","","","","","","","","","","","","","","","","","","","","","","","","","","","","","","","","","","","","","","","","","","","","","","","","","","","","","","","","","","","","","","","","","","","","","","","","","","","","","","","","","","","","","","","","","","","","","","","","","","","","","","","","","","","","","","","","","","","","","","","","","","","","","","","","","","","","","","","","","","","","","","","","","","","","","","","","","","","","","","","","","","","","","","","","","","","","","","","","","","","","","","","","","","","","","","","","","","","","","","","","","","","","","","","","","","","","","","","","","","","","","","","","","","","","","","","","","","","","","","","","","","","","","","","","","","","","","","","","","","","","","","","","","","","","","","","","","","","","","","","","","","","","","","","","","","","","","","","","","","","","","","","","","","","","","","","","","","","","","","","","","","","","","","","","","","","","","","","","","","","","","","","","","","","","","","","","","","","","","","","","","","","","","","","","","","","","","","","","","","","","","","","","","","","","","","","","","","","","","","","","","","","","","","","","","","","","","","","","","","","","","","","","","","","","","","","","","","","","","","","","","","","","","","","","","","","","","","","","","","","","","","","","","","","","","","","","","","","","","","","","","","","","","","","","","","","","","","","","","","","","","","","","","","","","","","","","","","","","","","","","","","","","","","","","","","","","","","","","","","","","","","","","","","","","","","","","","","","","","","","","","","","","","","","","","","","","","","","","","","","","","","","","","","","","","","","","","","","","","","","","","","","","","","","","","","","","","","","","","","","","","","","","","","","","","","","","","","","","","","","","","","","","","","","","","","","","","","","","","","","","","","","","","","","","","","","","","","","","","","","","","","","","","","","","","","","","","","","","","","","","","","","","","","","","","","","","","","","","","","","","","","","","","","","","","","","","","","","","","","","","","","","","","","","","","","","","","","","","","","","","","","","","","","","","","","","","","","","","","","","","","","","","","","","","","","","","","","","","","","","","","","","","","","","","","","","","","","","","","","","","","","","","","","","","","","","","","","","","","","","","","","","","","","","","","","","","","","","","","","","","","","","","","","","","","","","","","","","","","","","","","","","","","","","","","","","","","","","","","","","","","","","","","","","","","","","","","","","","","","","","","","","","","","","","","","","","","","","","","","","","","","","","","","","","","","","","","","","","","","","","","","","","","","","","","","","","","","","","","","","","","","","","","","","","","","","","","","","","","","","","","","","","","","","","","","","","","","","","","","","","","","","","","","","","","","","","","","","","","","","","","","","","","","","","","","","","","","","","","","","","","","","","","","","","","","","","","","","","","","","","","","","","","","","","","","","","","","","","","","","","","","","","","","","","","","","","","","","","","","","","","","","","","","","","","","","","","","","","","","","","","","","","","","","","","","","","","","","","","","","","","","","","","","","","","","","","","","","","","","","","","","","","","","","","","","","","","","","","","","","","","","","","","","","","","","","","","","","","","","","","","","","","","","","","","","","","","","","","","","","","","","","","","","","","","","","","","","","","","","","","","","","","","","","","","","","","","","","","","","","","","","","","","","","","","","","","","","","","","","","","","","","","","","","","","","","","","","","","","","","","","","","","","","","","","","","","","","","","","","","","","","","","","","","","","","","","","","","","","","","","","","","","","","","","","","","","","","","","","","","","","","","","","","","","","","","","","","","","","","","","","","","","","","","","","","","","","","","","","","","","","","","","","","","","","","","","","","","","","","","","","","","","","","","","","","","","","","","","","","","","","","","","","","","","","","","","","","","","","","","","","","","","","","","","","","","","","","","","","","","","","","","","","","","","","","","","","","","","","","","","","","","","","","","","","","","","","","","","","","","","","","","","","","","","","","","","","","","","","","","","","","","","","","","","","","","","","","","","","","","","","","","","","","","","","","","","","","","","","","","","","","","","","","","","","","","","","","","","","","","","","","","","","","","","","","","","","","","","","","","","","","","","","","","","","","","","","","","","","","","","","","","","","","","","","","","","","","","","","","","","","","","","","","","","","","","","","","","","","","","","","","","","","","","","","","","","","","","","","","","","","","","","","","","","","","","","","","","","","","","","","","","","","","","","","","","","","","","","","","","","","","","","","","","","","","","","","","","","","","","","","","","","","","","","","","","","","","","","","","","","","","","","","","","","","","","","","","","","","","","","","","","","","","","","","","","","","","","","","","","","","","","","","","","","","","","","","","","","","","","","","","","","","","","","","","","","","","","","","","","","","","","","","","","","","","","","","","","","","","","","","","","","","","","","","","","","","","","","","","","","","","","","","","","","","","","","","","","","","","","","","","","","","","","","","","","","","","","","","","","","","","","","","","","","","","","","","","","","","","","","","","","","","","","","","","","","","","","","","","","","","","","","","","","","","","","","","","","","","","","","","","","","","","","","","","","","","","","","","","","","","","","","","","","","","","","","","","","","","","","","","","","","","","","","","","","","","","","","","","","","","","","","","","","","","","","","","","","","","","","","","","","","","","","","","","","","","","","","","","","","","","","","","","","","","","","","","","","","","","","","","","","","","","","","","","","","","","","","","","","","","","","","","","","","","","","","","","","","","","","","","","","","","","","","","","","","","","","","","","","","","","","","","","","","","","","","","","","","","","","","","","","","","","","","","","","","","","","","","","","","","","","","","","","","","","","","","","","","","","","","","","","","","","","","","","","","","","","","","","","","","","","","","","","","","","","","","","","","","","","","","","","","","","","","","","","","","","","","","","","","","","","","","","","","","","","","","","","","","","","","","","","","","","","","","","","","","","","","","","","","","","","","","","","","","","","","","","","","","","","","","","","","","","","","","","","","","","","","","","","","","","","","","","","","","","","","","","","","","","","","","","","","","","","","","","","","","","","","","","","","","","","","","","","","","","","","","","","","","","","","","","","","","","","","","","","","","","","","","","","","","","","","","","","","","","","","","","","","","","","","","","","","","","","","","","","","","","","","","","","","","","","","","","","","","","","","","","","","","","","","","","","","","","","","","","","","","","","","","","","","","","","","","","","","","","","","","","","","","","","","","","","","","","","","","","","","","","","","","","","","","","","","","","","","","","","","","","","","","","","","","","","","","","","","","","","","","","","","","","","","","","","","","","","","","","","","","","","","","","","","","","","","","","","","","","","","","","","","","","","","","","","","","","","","","","","","","","","","","","","","","","","","","","","","","","","","","","","","","","","","","","","","","","","","","","","","","","","","","","","","","","","","","","","","","","","","","","","","","","","","","","","","","","","","","","","","","","","","","","","","","","","","","","","","","","","","","","","","","","","","","","","","","","","","","","","","","","","","","","","","","","","","","","","","","","","","","","","","","","","","","","","","","","","","","","","","","","","","","","","","","","","","","","","","","","","","","","","","","","","","","","","","","","","","","","","","","","","","","","","","","","","","","","","","","","","","","","","","","","","","","","","","","","","","","","","","","","","","","","","","","","","","","","","","","","","","","","","","","","","","","","","","","","","","","","","","","","","","","","","","","","","","","","","","","","","","","","","","","","","","","","","","","","","","","","","","","","","","","","","","","","","","","","","","","","","","","","","","","","","","","","","","","","","","","","","","","","","","","","","","","","","","","","","","","","","","","","","","","","","","","","","","","","","","","","","","","","","","","","","","","","","","","","","","","","","","","","","","","","","","","","","","","","","","","","","","","","","","","","","","","","","","","","","","","","","","","","","","","","","","","","","","","","","","","","","","","","","","","","","","","","","","","","","","","","","","","","","","","","","","","","","","","","","","","","","","","","","","","","","","","","","","","","","","","","","","","","","","","","","","","","","","","","","","","","","","","","","","","","","","","","","","","","","","","","","","","","","","","","","","","","","","","","","","","","","","","","","","","","","","","","","","","","","","","","","","","","","","","","","","","","","","","","","","","","","","","","","","","","","","","","","","","","","","","","","","","","","","","","","","","","","","","","","","","","","","","","","","","","","","","","","","","","","","","","","","","","","","","","","","","","","","","","","","","","","","","","","","","","","","","","","","","","","","","","","","","","","","","","","","","","","","","","","","","","","","","","","","","","","","","","","","","","","","","","","","","","","","","","","","","","","","","","","","","","","","","","","","","","","","","","","","","","","","","","","","","","","","","","","","","","","","","","","","","","","","","","","","","","","","","","","","","","","","","","","","","","","","","","","","","","","","","","","","","","","","","","","","","","","","","","","","","","","","","","","","","","","","","","","","","","","","","","","","","","","","","","","","","","","","","","","","","","","","","","","","","","","","","","","","","","","","","","","","","","","","","","","","","","","","","","","","","","","","","","","","","","","","","","","","","","","","","","","","","","","","","","","","","","","","","","","","","","","","","","","","","","","","","","","","","","","","","","","","","","","","","","","","","","","","","","","",""],"terms":{"basic":["Level","Lv","HP","HP","MP","MP","TP","TP","EXP","EXP"],"commands":["#{battletext.fight}","#{battletext.escape}","#{battletext.attack}","#{battletext.guard}","#{battletext.item}","Skill","#{yepshopmenucore.equip}","Status","Formation","Save","Game End","#{mainmenu.option}","#{msxinventory.weapon}","#{msxinventory.armor}","#{msxinventory.keyitems}","#{equip.equipment}","#{equip.optimize}","#{equip.clear}","#{mainmenu.newgame}","#{mainmenu.continue}",null,"#{mainmenu.totitle}","#{yepshopmenucore.cancel}",null,"#{yepshopmenucore.buy}","#{yepshopmenucore.sell}"],"params":["#{termwords.mhp} (MHP)","#{termwords.mmp} (MMP)","#{termwords.atk} (ATK)","#{termwords.def} (DEF)","#{termwords.mat} (MAT)","#{termwords.mdf} (MDF)","#{termwords.agi} (AGI)","#{termwords.luk} (LUK)","Hit","Evasion"],"messages":{"actionFailure":"#{messages.actionfail}","actorDamage":"#{messages.actordamage}","actorDrain":"#{messages.actordrain}","actorGain":"#{messages.actorgain}","actorLoss":"#{messages.actorloss}","actorNoDamage":"#{messages.actornodamage}","actorNoHit":"#{messages.actornohit}","actorRecovery":"#{messages.actorrecovery}","alwaysDash":"#{options.alwaysdash}","bgmVolume":"#{options.bgmvolume}","bgsVolume":"#{options.bgsvolume}","buffAdd":"#{messages.buffadd}","buffRemove":"#{messages.buffremove}","commandRemember":"#{options.commandremember}","counterAttack":"#{messages.counterattack}","criticalToActor":"#{messages.criticaltoactor}","criticalToEnemy":"#{messages.criticaltoenemy}","debuffAdd":"#{messages.debuffadd}","defeat":"#{messages.defeat}","emerge":"#{messages.emerge}","enemyDamage":"#{messages.enemydamage}","enemyDrain":"#{messages.enemydrain}","enemyGain":"#{messages.enemygain}","enemyLoss":"#{messages.enemyloss}","enemyNoDamage":"#{messages.enemynodamage}","enemyNoHit":"#{messages.enemynohit}","enemyRecovery":"#{messages.enemyrecovery}","escapeFailure":"#{messages.escapefail}","escapeStart":"#{messages.escapestart}","evasion":"#{messages.evasion}","expNext":"#{messages.expnext}","expTotal":"#{messages.exptotal}","file":"#{messages.file}","levelUp":"#{messages.levelup}","loadMessage":"#{messages.loadmessage}","magicEvasion":"#{messages.magicevasion}","magicReflection":"#{messages.magicreflection}","meVolume":"#{options.mevolume}","obtainExp":"#{messages.obtainexp}","obtainGold":"#{messages.obtaingold}","obtainItem":"#{messages.obtainitem}","obtainSkill":"#{messages.obtainskill}","partyName":"#{messages.partyname}","possession":"#{messages.possession}","preemptive":"#{messages.preemptive}","saveMessage":"#{messages.savemessage}","seVolume":"#{options.sevolume}","substitute":"#{messages.substitute}","surprise":"#{messages.surprise}","useItem":"#{messages.useitem}","victory":"#{messages.victory}"}},"testBattlers":[{"actorId":1,"equips":[1,1,2,3,0],"level":1},{"actorId":2,"equips":[2,1,2,3,0],"level":1},{"actorId":3,"equips":[3,0,2,3,4],"level":1},{"actorId":4,"equips":[4,0,2,3,4],"level":1}],"testTroopId":26,"title1Name":"","title2Name":"","titleBgm":{"name":"Wingless_Remotest-Liblary","pan":0,"pitch":100,"volume":100},"variables":["","Temp","Hidden Door Check","Hidden Door Check 2","Check Shop","Count Inside Magic Shop","Check Leader","4 Spheres","2 Torches","Check Times to Sandstorm 3","Number of Stone Set","Random Location X","Random Location Y","Number of Switchs Turned","Count Bridge Events","Torches Lit","Random Number","First Time To Luvinia","Counting Spirit Herbs","Number of Herbs Collected","Leader Max HP","ValenkaBoatFee","Ancient Runes Activated","Count For Self-Crafting Tutorial","Count For Breakable Tutorials","Use Kaoru's Vials","Cyan Vial","Violet Vial","Desc Cyan Vial","Desc Violet Vial","","","","","","","","","","","","","","","","","","","","","","","","","","","","","","","","","","","","","","","","","","","","","","","","","","","","","","","","","","","","","","","","","","","","","","","","","","","","","","","","","","","","","","","","","","","","","","","","","","","","","","","","","","","","","","","","","","","","","","","","","","","","","","","","","","","","","","","","","","","","","","","","","","","","","","","","","","","","","","","","","","","","","","","","","","","","","","","","","","","","","","","","","","","","","","","","","","","","","","","","","","","","","","","","","","","","","","","","","","","","","","","","","","","","","","","","","","","","","","","","","","","","","","","","","","","","","","","","","","","","","","","","","","","","","","","","","","","","","","","","","","","","","","","","","","","","","","","","","","","","","","","","","","","","","","","","","","","","","","","","","","","","","","","","","","","","","","","","","","","","","","","","","","","","","","","","","","","","","","","","","","","","","","","","","","","","","","","","","","","","","","","","","","","","","","","","","","","","","","","","","","","","","","","","","","","","","","","","","","","","","","","","","","","","","","","","","","","","","","","","","","","","","","","","","","","","","","","","","","","","","","","","","","","","","","","","2.Summerbreeze Weapon","2.Summerbreeze Armor","6.Seagull Weapon","6.Seagull Armor","7.Haravi Weapon","7.Haravi Armor","4.Religia Weapon","4.Religia Armor","11.Merin Weapon","11.Merin Armor","11.Merin Church","15.Luvinia Church","15.Luvinia Weapon","15.Luvinia Armor","18.Valenka Church","18.Valenka Weapon","18.Valenka Armor","20.Shiroyuki Church","20.Shiroyuki Weapon","20.Shiroyuki Armor","20.Serenus Church","20.Serenus Weapon","20.Serenus Armor","","","","","","","","","","","","","","","","","","","","","","","","","","","","","","","","","","","","","","","","","","","","","","","","","","","","","","","","","","","","","","","","","","","","","","","","","","","","","","","","","","","","","","","","","","","","","","","","","","","","","","","","","","","","","","","","","","","","","","","","","","","","","","","","","","","","","","","","","","","","","","","","","","","","","","","","","","","","","","","","","","","","","","","","","","","","","","","","","","","","","","","","","","","","","","","","","","","","","","","","","","","","","","","","","","","","","","","","","","","","","","","","","","","","","","","","","","","","","","","","","","","","","","","","","","","","","","","","","","","","","","","","","","","","","","","","","","","","","","Hour Var","Day Var","Year Var","Minute Var","Second Var","Day Week Var","Month Var","Season Var","Transfer Map Variable","Transfer Map X","Transfer Map Y","Oil Lamp Variable","Blanc's Soul Mates HP Req","Battle Tut Step","","","","","","","","","","","","","","","","","","","","","","","","","","","","","","","","","","","","","","","","","","","","","","","","","","","","","","","","","","","","","","","","","","","Actor 1 Level","Actor 2 Level","Actor 3 Level","Actor 4 Level","Actor 5 Level","Actor 6 Level","Party Mem 1 ID","Party Mem 2 ID","Party Mem 3 ID","Party Mem 4 ID","Party Mem 5 ID","Party Mem 6 ID","Total Party Length","Player Current Map ID","Player Map X","Player Map Y","Highest Level Actor","Temp Reset Skill Cost","Temp Count Total Skill","Temp Count Total Ulti","Party Mem 1 Level","Party Mem 2 Level","Party Mem 3 Level","Party Mem 4 Level","Total Level of Party","Average Level of Party","Party Length","Party Mem 5 Level","Party Mem 6 Level","Target Pos X","Target Pos Y","Action Random Number","Temp Reset Stat Cost","Temp JP Spent","Inn Cost","Quest Step Counter","Player Direction","Player Map ID","[Ending] Corrupted Lilith","Auto Battle Var","Highest Total JP","","","","","","","","","","","","","","","","","","","","Stored Party Mem 1","Stored Party Mem 2","Stored Party Mem 3","Stored Party Mem 4","Stored Party Mem 5","Stored Party Mem 6","Potential Map X","Potential Map Y","Potential Map ID","","","","","","\\i[167]Spirit","","","","","------Actor 5 Stats-----","\\i[164]Vitality","\\i[162]Strength","\\i[165]Dexterity","\\i[166]Intelligence","\\i[167]Spirit","","","","","------Actor 7 Stats-----","\\i[164]Vitality","\\i[162]Strength","\\i[165]Dexterity","\\i[166]Intelligence","\\i[167]Spirit","","","","","","","","","","","","","","","","","","","","","","","","","","Text Box Var","Cheat Split Value","","","","","","","","","","","","","","","","","","","","","","","","","","","","","","","","","","","","","","","","","","","","","","","","","","","","","","","","","","","","","","","","","","","","","","","","","","","","","","","","","","","","","","","","","","","","","","","","","","","","","","","","","","","","","","","","","","","","","","","","","","","","","","","","","","","","","","","","","","","","","","","","","","","","","","","","","","","","","","","","","","","","","","","","","","","","","","","","","","","","","","","","","","","","","","","","","","","","","","","","","","","","","","","","","","","","","","","","","","","","","","","","","","","","","","","","","","","","","","","","","","","","","","","","","","","","","","","","","","","","","","","","","","","","","","","","","","","","","","","","","","","","","","","","","","","","","","","","","","","","","","","","","","","","","","","","","","","","","","","","","","","","","","","","","","","","","","","","","","","","","","","","","","","","","","","","","","","","","","","","","","","","","","","","","","","","","","","","","","","","","","","","","","","","","","","","","","","","","","","","","","","","","","","","","","","","","","","","","","","","","","","","","","","","","","","","","","","","","","","","","","","","","","","","","","","","","","","","","","","","","","","","","","","","","","","","","","","","","","","","","","","","","","","","","","","","","","","","","","","<<Actor1ActiveSkills>>#{yepactorvar.active}","<<Actor1PassiveSkills>>#{yepactorvar.passive}","<<Actor1Ultimate>>#{yepactorvar.ultimate}","<<Actor1TotalSkills>>#{yepactorvar.totallearn}","<<Actor1MaxPassive>>#{yepactorvar.maxpassive}","<<Actor1MaxTotal>>#{yepactorvar.maxtotal}","<<Actor1MaxUlti>>#{yepactorvar.maxulti}","<<Actor1MaxActive>>#{yepactorvar.maxactive}","","","<<Actor2ActiveSkills>>#{yepactorvar.active}","<<Actor2PassiveSkills>>#{yepactorvar.passive}","<<Actor2Ultimate>>#{yepactorvar.ultimate}","<<Actor2TotalSkills>>#{yepactorvar.totallearn}","<<Actor2MaxPassive>>#{yepactorvar.maxpassive}","<<Actor2MaxTotal>>#{yepactorvar.maxtotal}","<<Actor2MaxUlti>>#{yepactorvar.maxulti}","<<Actor2MaxActive>>#{yepactorvar.maxactive}","","","<<Actor3ActiveSkills>>#{yepactorvar.active}","<<Actor3PassiveSkills>>#{yepactorvar.passive}","<<Actor3Ultimate>>#{yepactorvar.ultimate}","<<Actor3TotalSkills>>#{yepactorvar.totallearn}","<<Actor3MaxPassive>>#{yepactorvar.maxpassive}","<<Actor3MaxTotal>>#{yepactorvar.maxtotal}","<<Actor3MaxUlti>>#{yepactorvar.maxulti}","<<Actor3MaxActive>>#{yepactorvar.maxactive}","","","<<Actor4ActiveSkills>>#{yepactorvar.active}","<<Actor4PassiveSkills>>#{yepactorvar.passive}","<<Actor4Ultimate>>#{yepactorvar.ultimate}","<<Actor4TotalSkills>>#{yepactorvar.totallearn}","<<Actor4MaxPassive>>#{yepactorvar.maxpassive}","<<Actor4MaxTotal>>#{yepactorvar.maxtotal}","<<Actor4MaxUlti>>#{yepactorvar.maxulti}","<<Actor4MaxActive>>#{yepactorvar.maxactive}","","","<<Actor5ActiveSkills>>#{yepactorvar.active}","<<Actor5PassiveSkills>>#{yepactorvar.passive}","<<Actor5Ultimate>>#{yepactorvar.ultimate}","<<Actor5TotalSkills>>#{yepactorvar.totallearn}","<<Actor5MaxPassive>>#{yepactorvar.maxpassive}","<<Actor5MaxTotal>>#{yepactorvar.maxtotal}","<<Actor5MaxUlti>>#{yepactorvar.maxulti}","<<Actor5MaxActive>>#{yepactorvar.maxactive}","","","<<Actor6ActiveSkills>>#{yepactorvar.active}","<<Actor6PassiveSkills>>#{yepactorvar.passive}","<<Actor6Ultimate>>#{yepactorvar.ultimate}","<<Actor6TotalSkills>>#{yepactorvar.totallearn}","<<Actor6MaxPassive>>#{yepactorvar.maxpassive}","<<Actor6MaxTotal>>#{yepactorvar.maxtotal}","<<Actor6MaxUlti>>#{yepactorvar.maxulti}","<<Actor6MaxActive>>#{yepactorvar.maxactive}","","","","","","","","","","","","","","","","","","","","","","","","","","","","","","","","","","","","","","","","","","","","","","","","","","","","","","","","","","","","","","","","","","","","","","","","","","","","","","","","","","","","","","","","","","","","","","","","","","","","","","","","","","","","","","","","","","","","","","","","","","","","","","","","","","","","","","","","","","","","","","","","","","","","","","","","","","","","","","","","","","","","","","","","","","","","","","","","","","","","","","","","","","","","","","","","","","","","","","","","","","","","","","","","","","","","","","","","","","","","","","","","","","","","","","","","","","","","","","","","","","","","","","","","","","","","","","","","","","","","","","","","","","","","","","","","","","","","","","","","","","","","","","","","","","","","","","","","","","","","","","","","","","","","","","","","","","","","","","","","","","","","","","","","","","","","","","","","","","","","","","","","","","","","","","","","","","","","","","","","","","","","","","","","","","","","","","","","","","","","","","","","","","","","","","","","","","","","","","","","","","","","","","","","","","","","","","","","","","","","","","","","","","","","","","","","","","","","","","","","","","","","","","","","","","","","","","","","","","","","","","","","","","","","","","","","","","","","","","","","","","","","","","","","","","","","","","","","","","","","","","","","","","","","","","","","","","","","","","","","","","","","","","","","","","","","","","","","","","","","","","","","","","","","","","","","","","","","","","","","","","","","","","","","","","","","","","","","","","","","","","","","","","","","","","","","","","","","","","","","","","","","","","","","","","","","","","","","","","","","","","","","","","","","","","","","","","","","","","","","","","","","","","","","","","","","","","","","","","","","","","","","","","","","","","","","","","","","","","","","","","","","","","","","","","","","","","","","","","","","","","","","","","","","","","","","","","","","","","","","","","","","","","","","","","","","","","","","","","","","","","","","","","","","","","","","","","","","","","","","","","","","","","","","","","","","","","","","","","","","","","","","","","","","","","","","","","","","","","","","","","","","","","","","","","","","","","","","","","","","","","","","","","","","","","","","","","","","","","","","","","","","","","","","","","","","","","","","","","","","","","","","","","","","","","","","","","","","","","","","","","","","","","","","","","","","","","","","","","","","","","","","","","","","","","","","","","","","","","","","","","","","","","","","","","","","","","","","","","","","","","","","","","","","","","","","","","","","","","","","","","","","","","","","","","","","","","","","","","","","","","","","","","","","","","","","","","","","","","","","","","","","","","","","","","","","","","","","","","","","","","","","","","","","","","","","","","","","","","","","","","","","","","","","","","","","","","","","","","","","","","","","","","","","","","","","","","","","","","","","","","","","","","","","","","","","","","","","","","","","","","","","","","","","","","","","","","","","","","","","","","","","","","","","","","","","","","","","","","","","","","","","","","","","","","","","","","","","","","","","","","","","","","","","","","","","","","","","","","","","","","","","","","","","","","","","","","","","","","","","","","","","","","","","","","","","","","","","","","","","","","","","","","","","","","","","","","","","","","","","","","","","","","","","","","","","","","","","","","","","","","","","","","","","","","","","","","","","","","","","","","","","","","","","","","","","","","","","","","","","","","","","","","","","","","","","","","","","","","","","","","","","","","","","","","","","","","","","","","","","","","","","","","","","","","","","","","","","","","","","","","","","","","","","","","","","","","","","","","","","","","","","","","","","","","","","","","","","","","","","","","","","","","","","","","","","","","","","","","","","","","","","","","","","","","","","","","","","","","","","","","","","","","","","","","","","","","","","","","","","","","","","","","","","","","","","","","","","","","","","","","","","","","","","","","","","","","","","","","","","","","","","","","","","","","","","","","","","","","","","","","","","","","","","","","","","","","","","","","","","","","","","","","","","","","","","","","","","","","","","","","","","","","","","","","","","","","","","","","","","","","","","","","","","","","","","","","","","","","","","","","","","","","","","","","","","","","","","","","","","","","","","","","","","","","","","","","","","","","","","","","","","","","","","","","","","","","","","","","","","","","","","","","","","","","","","","","","","","","","","","","","","","","","","","","","","","","","","","","","","","","","","","","","","","","","","","","","","","","","","","","","","","","","","","","","","","","","","","","","","","","","","","","","","","","","","","","","","","","","","","","","","","","","","","","","","","","","","","","","","","","","","","","","","","","","","","","","","","","","","","","","","","","","","","","","","","","","","","","","","","","","","","","","","","","","","","","","","","","","","","","","","","","","","","","","","","","","","","","","","","","","","","","","","","","","","","","","","","","","","","","","","","","","","","","","","","","","","","","","","","","","","","","","","","","","","","","","","","","","","","","","","","","","","","","","","","","","","","","","","","","","","","","","","","","","","","","","","","","","","","","","","","","","","","","","","","","","","","","","","","","","","","","","","","","","","","","","","","","","","","","","","","","","","","","","","","","","","","","","","","","","","","","","","","","","","","","","","","","","","","","","","","","","","","","","","","","","","","","","","","","","","","","","","","","","","","","","","","","","","","","","","","","","","","","","","","","","","","","","","","","","","","","","","","","","","","","","","","","","","","","","","","","","","","","","","","","","","","","","","","","","","","","","","","","","","","","","","","","","","","","","","","","","","","","","","","","","","","","","","","","","","","","","","","","","","","","","","","","","","","","","","","","","","","","","","","","","","","","","","","","","","","","","","","","","","","","","","","","","","","","","","","","","","","","","","","","","","","","","","","","","","","","","","","","","","","","","","","","","","","","","","","","","","","","","","","","","","","","","","","","","","","","","","","","","","","","","","","","","","","","","","","","","","","","","","","","","","","","","","","","","","","","","","","","","","","","","","","","","","","","","","","","","","","","","","","","","","","","","","","","","","","","","","","","","","","","","","","","","","","","","","","","","","","","","","","","","","","","","","","","","","","","","","","","","","","","","","","","","","","","","","","","","","","","","","","","","","","","","","","","","","","","","","","","","","","","","","","","","","","","","","","","","","","","","","","","","","","","","","","","","","","","","","","","","","","","","","","","","","","","","","","","","","","","","","","","","","","","","","","","","","","","","","","","","","","","","","","","","","","","","","","","","","","","","","","","","","","","","","","","","","","","","","","","","","","","","","","","","","","","","","","","","","","","","","","","","","","","","","","","","","","","","","","","","","","","","","","","","","","","","","","","","","","","","","","","","","","","","","","","","","","","","","","","","","","","","","","","","","","","","","","","","","","","","","","","","","","","","","","","","","","","","","","","","","","","","","","","","","","","","","","","","","","","","","","","","","","","","","","","","","","","","","","","","","","","","","","","","","","","","","","","","","","","","","","","","","","","","","","","","","","","","","","","","","","","","","","","","","","","","","","","","","","","","","","","","","","","","","","","","","","","","","","","","","","","","","","","","","","","","","","","","","","","","","","","","","","","","","","","","","","","","","","","","","","","","","","","","","","","","","","","","","","","","","","","","","","","","","","","","","","","","","","","","","","","","","","","","","","","","","","","","","","","","","","","","","","","","","","","","","","","","","","","","","","","","","","","","","","","","","","","","","","","","","","","","","","","","","","","","","","","","","","","","","","","","","","","","","","","","","","","","","","","","","","","","","","","","","","","","","","","","","","","","","","","","","","","","","","","","","","","","","","","","","","","","","","","","","","","","","","","","","","","","","","","","","","","","","","","","","","","","","","","","","","","","","","","","","","","","","","","","","","","","","","","","","","","","","","","","","","","","","","","","","","","","","","","","","","","","","","","","","","","","","","","","","","","","","","","","","","","","","","","","","","","","","","","","","","","","","","","","","","","","","","","","","","","","","","","","","","","","","","","","","","","","","","","","","","","","","","","","","","","","","","","","","","","","","","","","","","","","","","","","","","","","","","","","","","","","","","","","","","","","","","","","","","","","","","","","","","","","","","","","","","","","","","","","","","","","","","","","","","","","","","","","","","","","","","","","","","","","","","","","","","","","","","","","","","","","","","","","","","","","","","","","","","","","","","","","","","","","","","","","","","","","","","","","","","","","","","","","","","","","","","","","","","","","","","","","","","","","","","","","","","","","","","","","","","","","","","","","","","","","","","","","","","","","","","",""],"versionId":3759880,"victoryMe":{"name":"Wingless_Victory","pan":0,"pitch":100,"volume":90},"weaponTypes":["","#{termwords.dagger}","#{termwords.sword}","#{termwords.flail}","#{termwords.axe}","#{termwords.whip}","#{termwords.staff}","#{termwords.bow}","#{termwords.crossbow}","#{termwords.gun}","#{termwords.claw}","#{termwords.gauntlet}","#{termwords.spear}","#{termwords.magictome}","Magic Blaster","","","","","","","","","","","","","","","",""],"windowTone":[0,0,0,0],"hasEncryptedImages":true,"hasEncryptedAudio":true,"encryptionKey":"e10adc3949ba59abbe56e057f20f883e"}